CHANGES.txt
CONTRIBUTORS.txt
MANIFEST.in
README.txt
setup.py
collective/__init__.py
collective.maps.geoxml.egg-info/PKG-INFO
collective.maps.geoxml.egg-info/SOURCES.txt
collective.maps.geoxml.egg-info/dependency_links.txt
collective.maps.geoxml.egg-info/entry_points.txt
collective.maps.geoxml.egg-info/namespace_packages.txt
collective.maps.geoxml.egg-info/not-zip-safe
collective.maps.geoxml.egg-info/requires.txt
collective.maps.geoxml.egg-info/top_level.txt
collective/maps/__init__.py
collective/maps/geoxml/README.txt
collective/maps/geoxml/__init__.py
collective/maps/geoxml/config.py
collective/maps/geoxml/configure.zcml
collective/maps/geoxml/interfaces.py
collective/maps/geoxml/tests.py
collective/maps/geoxml/browser/__init__.py
collective/maps/geoxml/browser/configure.zcml
collective/maps/geoxml/browser/data.kml.pt
collective/maps/geoxml/browser/egeoxml.js
collective/maps/geoxml/browser/view.pt
collective/maps/geoxml/content/__init__.py
collective/maps/geoxml/content/configure.zcml
collective/maps/geoxml/content/geoxml.py
collective/maps/geoxml/portlets/__init__.py
collective/maps/geoxml/portlets/configure.zcml
collective/maps/geoxml/profiles/default/factorytool.xml
collective/maps/geoxml/profiles/default/metadata.xml
collective/maps/geoxml/profiles/default/portlets.xml
collective/maps/geoxml/profiles/default/rolemap.xml
collective/maps/geoxml/profiles/default/types.xml
collective/maps/geoxml/profiles/default/types/GeoXml.xml
collective/maps/geoxml/tests/__init__.py
collective/maps/geoxml/tests/doc_tests.py
docs/CascinaPolo.kml
docs/HISTORY.txt
docs/INSTALL.txt
docs/LICENSE.GPL
docs/LICENSE.txt