Metadata-Version: 1.0
Name: collective.maps.geoxml
Version: 1.0
Summary: A content for kml file.
Home-page: http://www.reflab.it
Author: Riccardo Lemmi
Author-email: riccardo@reflab.it
License: GPL
Keywords: kml geoxml maps
Platform: UNKNOWN
Classifier: Framework :: Plone
Classifier: Intended Audience :: Developers
Classifier: Topic :: Software Development :: Libraries :: Python Modules
Classifier: License :: OSI Approved :: GNU General Public License (GPL)
